mantas_z_mod1_atsiskaitymas/__init__.py
mantas_z_mod1_atsiskaitymas/benu_crawler.py
mantas_z_mod1_atsiskaitymas/crawler.py
mantas_z_mod1_atsiskaitymas/gintarine_crawler.py
tests/__init__.py
tests/tests.py
mantas_z_mod1_atsiskaitymas-0.1.0.dist-info/METADATA
mantas_z_mod1_atsiskaitymas-0.1.0.dist-info/WHEEL
mantas_z_mod1_atsiskaitymas-0.1.0.dist-info/top_level.txt
mantas_z_mod1_atsiskaitymas-0.1.0.dist-info/RECORD
