Metadata-Version: 2.1
Name: mantas_z_mod1_atsiskaitymas
Version: 0.1.0
Author: Mantas
Author-email: 
Requires-Python: >=3.10
Requires-Dist: certifi==2024.8.30
Requires-Dist: charset-normalizer==3.4.0
Requires-Dist: idna==3.10
Requires-Dist: lxml==5.3.0
Requires-Dist: requests==2.32.3
Requires-Dist: setuptools==75.5.0
Requires-Dist: urllib3==2.2.3
